<?xml version="1.0" ?>
<annotation>
	<folder>JPEGImages</folder>
	<filename>005539f4a1934d69b4f9a18e941cb73b_170</filename>
	<path>C:/AIoT/Projects/keras-yolo3-master/VOCdevkit/VOC2007/JPEGImages/005539f4a1934d69b4f9a18e941cb73b_170.jpg</path>
	<source>
		<database>Unknown</database>
	</source>
	<size>
		<width>1920</width>
		<height>1080</height>
		<depth>3</depth>
	</size>
	<segmented>0</segmented>
	<object>
		<name>person</name>
		<pose>Unspecified</pose>
		<truncated>0</truncated>
		<difficult>0</difficult>
		<bndbox>
			<xmin>1499.32</xmin>
			<ymin>530.60</ymin>
			<xmax>1518.30</xmax>
			<ymax>575.30</ymax>
		</bndbox>
	</object>
	<object>
		<name>person</name>
		<pose>Unspecified</pose>
		<truncated>0</truncated>
		<difficult>0</difficult>
		<bndbox>
			<xmin>1620.55</xmin>
			<ymin>539.91</ymin>
			<xmax>1642.84</xmax>
			<ymax>606.04</ymax>
		</bndbox>
	</object>
	<object>
		<name>person</name>
		<pose>Unspecified</pose>
		<truncated>0</truncated>
		<difficult>0</difficult>
		<bndbox>
			<xmin>1209.24</xmin>
			<ymin>519.91</ymin>
			<xmax>1216.86</xmax>
			<ymax>536.42</ymax>
		</bndbox>
	</object>
</annotation>
