<?xml version="1.0" ?>
<annotation>
	<folder>JPEGImages</folder>
	<filename>07014fcfaf595a588e6ca89383e9affa_100</filename>
	<path>C:/AIoT/Projects/keras-yolo3-master/VOCdevkit/VOC2007/JPEGImages/07014fcfaf595a588e6ca89383e9affa_100.jpg</path>
	<source>
		<database>Unknown</database>
	</source>
	<size>
		<width>1920</width>
		<height>1080</height>
		<depth>3</depth>
	</size>
	<segmented>0</segmented>
	<object>
		<name>person</name>
		<pose>Unspecified</pose>
		<truncated>0</truncated>
		<difficult>0</difficult>
		<bndbox>
			<xmin>1798.06</xmin>
			<ymin>596.07</ymin>
			<xmax>1818.02</xmax>
			<ymax>666.10</ymax>
		</bndbox>
	</object>
	<object>
		<name>person</name>
		<pose>Unspecified</pose>
		<truncated>0</truncated>
		<difficult>0</difficult>
		<bndbox>
			<xmin>653.76</xmin>
			<ymin>560.65</ymin>
			<xmax>709.13</xmax>
			<ymax>677.41</ymax>
		</bndbox>
	</object>
	<object>
		<name>person</name>
		<pose>Unspecified</pose>
		<truncated>0</truncated>
		<difficult>0</difficult>
		<bndbox>
			<xmin>1677.88</xmin>
			<ymin>588.19</ymin>
			<xmax>1707.28</xmax>
			<ymax>637.90</ymax>
		</bndbox>
	</object>
	<object>
		<name>person</name>
		<pose>Unspecified</pose>
		<truncated>0</truncated>
		<difficult>0</difficult>
		<bndbox>
			<xmin>1903.10</xmin>
			<ymin>616.50</ymin>
			<xmax>1920.00</xmax>
			<ymax>695.84</ymax>
		</bndbox>
	</object>
</annotation>
