<?xml version="1.0" ?>
<annotation>
	<folder>JPEGImages</folder>
	<filename>1a6de2d182f6d79190d8b1de2e1a78af_620</filename>
	<path>C:/AIoT/Projects/keras-yolo3-master/VOCdevkit/VOC2007/JPEGImages/1a6de2d182f6d79190d8b1de2e1a78af_620.jpg</path>
	<source>
		<database>Unknown</database>
	</source>
	<size>
		<width>1920</width>
		<height>1080</height>
		<depth>3</depth>
	</size>
	<segmented>0</segmented>
	<object>
		<name>person</name>
		<pose>Unspecified</pose>
		<truncated>0</truncated>
		<difficult>0</difficult>
		<bndbox>
			<xmin>1549.19</xmin>
			<ymin>279.92</ymin>
			<xmax>1575.33</xmax>
			<ymax>375.30</ymax>
		</bndbox>
	</object>
	<object>
		<name>person</name>
		<pose>Unspecified</pose>
		<truncated>0</truncated>
		<difficult>0</difficult>
		<bndbox>
			<xmin>1309.66</xmin>
			<ymin>272.46</ymin>
			<xmax>1340.14</xmax>
			<ymax>344.00</ymax>
		</bndbox>
	</object>
	<object>
		<name>person</name>
		<pose>Unspecified</pose>
		<truncated>0</truncated>
		<difficult>0</difficult>
		<bndbox>
			<xmin>1868.81</xmin>
			<ymin>279.20</ymin>
			<xmax>1920.00</xmax>
			<ymax>492.00</ymax>
		</bndbox>
	</object>
	<object>
		<name>person</name>
		<pose>Unspecified</pose>
		<truncated>0</truncated>
		<difficult>0</difficult>
		<bndbox>
			<xmin>1423.97</xmin>
			<ymin>276.54</ymin>
			<xmax>1454.63</xmax>
			<ymax>367.50</ymax>
		</bndbox>
	</object>
</annotation>
