<?xml version="1.0" ?>
<annotation>
	<folder>JPEGImages</folder>
	<filename>1df3c48b1f0c7a7626871e7465b19ead_410</filename>
	<path>C:/AIoT/Projects/keras-yolo3-master/VOCdevkit/VOC2007/JPEGImages/1df3c48b1f0c7a7626871e7465b19ead_410.jpg</path>
	<source>
		<database>Unknown</database>
	</source>
	<size>
		<width>1920</width>
		<height>1080</height>
		<depth>3</depth>
	</size>
	<segmented>0</segmented>
	<object>
		<name>person</name>
		<pose>Unspecified</pose>
		<truncated>0</truncated>
		<difficult>0</difficult>
		<bndbox>
			<xmin>207.59</xmin>
			<ymin>181.81</ymin>
			<xmax>258.49</xmax>
			<ymax>254.10</ymax>
		</bndbox>
	</object>
	<object>
		<name>person</name>
		<pose>Unspecified</pose>
		<truncated>0</truncated>
		<difficult>0</difficult>
		<bndbox>
			<xmin>421.31</xmin>
			<ymin>174.29</ymin>
			<xmax>476.18</xmax>
			<ymax>237.50</ymax>
		</bndbox>
	</object>
	<object>
		<name>person</name>
		<pose>Unspecified</pose>
		<truncated>0</truncated>
		<difficult>0</difficult>
		<bndbox>
			<xmin>7.13</xmin>
			<ymin>194.45</ymin>
			<xmax>40.39</xmax>
			<ymax>263.31</ymax>
		</bndbox>
	</object>
	<object>
		<name>person</name>
		<pose>Unspecified</pose>
		<truncated>0</truncated>
		<difficult>0</difficult>
		<bndbox>
			<xmin>493.37</xmin>
			<ymin>185.50</ymin>
			<xmax>521.88</xmax>
			<ymax>230.46</ymax>
		</bndbox>
	</object>
</annotation>
