<?xml version="1.0" ?>
<annotation>
	<folder>JPEGImages</folder>
	<filename>288be7d776a6f3e284ff3978722d9ad3_380</filename>
	<path>C:/AIoT/Projects/keras-yolo3-master/VOCdevkit/VOC2007/JPEGImages/288be7d776a6f3e284ff3978722d9ad3_380.jpg</path>
	<source>
		<database>Unknown</database>
	</source>
	<size>
		<width>1920</width>
		<height>1080</height>
		<depth>3</depth>
	</size>
	<segmented>0</segmented>
	<object>
		<name>person</name>
		<pose>Unspecified</pose>
		<truncated>0</truncated>
		<difficult>0</difficult>
		<bndbox>
			<xmin>867.23</xmin>
			<ymin>168.76</ymin>
			<xmax>954.20</xmax>
			<ymax>445.10</ymax>
		</bndbox>
	</object>
	<object>
		<name>person</name>
		<pose>Unspecified</pose>
		<truncated>0</truncated>
		<difficult>0</difficult>
		<bndbox>
			<xmin>495.57</xmin>
			<ymin>141.16</ymin>
			<xmax>585.25</xmax>
			<ymax>379.60</ymax>
		</bndbox>
	</object>
	<object>
		<name>person</name>
		<pose>Unspecified</pose>
		<truncated>0</truncated>
		<difficult>0</difficult>
		<bndbox>
			<xmin>728.09</xmin>
			<ymin>199.93</ymin>
			<xmax>744.96</xmax>
			<ymax>230.80</ymax>
		</bndbox>
	</object>
	<object>
		<name>person</name>
		<pose>Unspecified</pose>
		<truncated>0</truncated>
		<difficult>0</difficult>
		<bndbox>
			<xmin>429.01</xmin>
			<ymin>144.44</ymin>
			<xmax>517.26</xmax>
			<ymax>401.10</ymax>
		</bndbox>
	</object>
	<object>
		<name>person</name>
		<pose>Unspecified</pose>
		<truncated>0</truncated>
		<difficult>0</difficult>
		<bndbox>
			<xmin>119.62</xmin>
			<ymin>203.07</ymin>
			<xmax>145.49</xmax>
			<ymax>297.83</ymax>
		</bndbox>
	</object>
	<object>
		<name>person</name>
		<pose>Unspecified</pose>
		<truncated>0</truncated>
		<difficult>0</difficult>
		<bndbox>
			<xmin>149.35</xmin>
			<ymin>210.98</ymin>
			<xmax>170.47</xmax>
			<ymax>279.28</ymax>
		</bndbox>
	</object>
	<object>
		<name>person</name>
		<pose>Unspecified</pose>
		<truncated>0</truncated>
		<difficult>0</difficult>
		<bndbox>
			<xmin>1022.72</xmin>
			<ymin>187.33</ymin>
			<xmax>1107.35</xmax>
			<ymax>388.32</ymax>
		</bndbox>
	</object>
</annotation>
