<?xml version="1.0" ?>
<annotation>
	<folder>JPEGImages</folder>
	<filename>288be7d776a6f3e284ff3978722d9ad3_660</filename>
	<path>C:/AIoT/Projects/keras-yolo3-master/VOCdevkit/VOC2007/JPEGImages/288be7d776a6f3e284ff3978722d9ad3_660.jpg</path>
	<source>
		<database>Unknown</database>
	</source>
	<size>
		<width>1920</width>
		<height>1080</height>
		<depth>3</depth>
	</size>
	<segmented>0</segmented>
	<object>
		<name>person</name>
		<pose>Unspecified</pose>
		<truncated>0</truncated>
		<difficult>0</difficult>
		<bndbox>
			<xmin>1001.50</xmin>
			<ymin>220.19</ymin>
			<xmax>1018.29</xmax>
			<ymax>273.30</ymax>
		</bndbox>
	</object>
</annotation>
