<?xml version="1.0" ?>
<annotation>
	<folder>JPEGImages</folder>
	<filename>28b491917cf8962c935e9d9ab414fb1f_120</filename>
	<path>C:/AIoT/Projects/keras-yolo3-master/VOCdevkit/VOC2007/JPEGImages/28b491917cf8962c935e9d9ab414fb1f_120.jpg</path>
	<source>
		<database>Unknown</database>
	</source>
	<size>
		<width>1920</width>
		<height>1080</height>
		<depth>3</depth>
	</size>
	<segmented>0</segmented>
	<object>
		<name>person</name>
		<pose>Unspecified</pose>
		<truncated>0</truncated>
		<difficult>0</difficult>
		<bndbox>
			<xmin>725.25</xmin>
			<ymin>356.32</ymin>
			<xmax>738.32</xmax>
			<ymax>386.69</ymax>
		</bndbox>
	</object>
	<object>
		<name>person</name>
		<pose>Unspecified</pose>
		<truncated>0</truncated>
		<difficult>0</difficult>
		<bndbox>
			<xmin>794.24</xmin>
			<ymin>359.30</ymin>
			<xmax>808.78</xmax>
			<ymax>405.63</ymax>
		</bndbox>
	</object>
	<object>
		<name>person</name>
		<pose>Unspecified</pose>
		<truncated>0</truncated>
		<difficult>0</difficult>
		<bndbox>
			<xmin>807.87</xmin>
			<ymin>362.47</ymin>
			<xmax>820.72</xmax>
			<ymax>404.60</ymax>
		</bndbox>
	</object>
</annotation>
