<?xml version="1.0" ?>
<annotation>
	<folder>JPEGImages</folder>
	<filename>28d65e146cce193670d4944bcae35ee6_620</filename>
	<path>C:/AIoT/Projects/keras-yolo3-master/VOCdevkit/VOC2007/JPEGImages/28d65e146cce193670d4944bcae35ee6_620.jpg</path>
	<source>
		<database>Unknown</database>
	</source>
	<size>
		<width>1920</width>
		<height>1080</height>
		<depth>3</depth>
	</size>
	<segmented>0</segmented>
	<object>
		<name>person</name>
		<pose>Unspecified</pose>
		<truncated>0</truncated>
		<difficult>0</difficult>
		<bndbox>
			<xmin>1180.89</xmin>
			<ymin>516.22</ymin>
			<xmax>1211.78</xmax>
			<ymax>608.80</ymax>
		</bndbox>
	</object>
	<object>
		<name>person</name>
		<pose>Unspecified</pose>
		<truncated>0</truncated>
		<difficult>0</difficult>
		<bndbox>
			<xmin>500.00</xmin>
			<ymin>490.58</ymin>
			<xmax>525.67</xmax>
			<ymax>570.23</ymax>
		</bndbox>
	</object>
	<object>
		<name>person</name>
		<pose>Unspecified</pose>
		<truncated>0</truncated>
		<difficult>0</difficult>
		<bndbox>
			<xmin>673.55</xmin>
			<ymin>494.00</ymin>
			<xmax>704.23</xmax>
			<ymax>575.99</ymax>
		</bndbox>
	</object>
	<object>
		<name>person</name>
		<pose>Unspecified</pose>
		<truncated>0</truncated>
		<difficult>0</difficult>
		<bndbox>
			<xmin>1829.92</xmin>
			<ymin>537.25</ymin>
			<xmax>1867.19</xmax>
			<ymax>629.52</ymax>
		</bndbox>
	</object>
</annotation>
