<?xml version="1.0" ?>
<annotation>
	<folder>JPEGImages</folder>
	<filename>2aae90bdd44bff9d96bbf7899df2f2c7_630</filename>
	<path>C:/AIoT/Projects/keras-yolo3-master/VOCdevkit/VOC2007/JPEGImages/2aae90bdd44bff9d96bbf7899df2f2c7_630.jpg</path>
	<source>
		<database>Unknown</database>
	</source>
	<size>
		<width>1920</width>
		<height>1080</height>
		<depth>3</depth>
	</size>
	<segmented>0</segmented>
	<object>
		<name>person</name>
		<pose>Unspecified</pose>
		<truncated>0</truncated>
		<difficult>0</difficult>
		<bndbox>
			<xmin>842.89</xmin>
			<ymin>467.01</ymin>
			<xmax>865.97</xmax>
			<ymax>525.13</ymax>
		</bndbox>
	</object>
</annotation>
