<?xml version="1.0" ?>
<annotation>
	<folder>JPEGImages</folder>
	<filename>32f7accc4d28d7e210ae5b12b9e62c8d_30</filename>
	<path>C:/AIoT/Projects/keras-yolo3-master/VOCdevkit/VOC2007/JPEGImages/32f7accc4d28d7e210ae5b12b9e62c8d_30.jpg</path>
	<source>
		<database>Unknown</database>
	</source>
	<size>
		<width>1920</width>
		<height>1080</height>
		<depth>3</depth>
	</size>
	<segmented>0</segmented>
	<object>
		<name>person</name>
		<pose>Unspecified</pose>
		<truncated>0</truncated>
		<difficult>0</difficult>
		<bndbox>
			<xmin>1105.12</xmin>
			<ymin>417.23</ymin>
			<xmax>1128.97</xmax>
			<ymax>442.53</ymax>
		</bndbox>
	</object>
	<object>
		<name>person</name>
		<pose>Unspecified</pose>
		<truncated>0</truncated>
		<difficult>0</difficult>
		<bndbox>
			<xmin>1077.94</xmin>
			<ymin>412.29</ymin>
			<xmax>1100.17</xmax>
			<ymax>439.40</ymax>
		</bndbox>
	</object>
	<object>
		<name>person</name>
		<pose>Unspecified</pose>
		<truncated>0</truncated>
		<difficult>0</difficult>
		<bndbox>
			<xmin>914.84</xmin>
			<ymin>414.32</ymin>
			<xmax>929.58</xmax>
			<ymax>436.94</ymax>
		</bndbox>
	</object>
</annotation>
