<?xml version="1.0" ?>
<annotation>
	<folder>JPEGImages</folder>
	<filename>3f14e5b775c1af77b3ee9dad6090e842_540</filename>
	<path>C:/AIoT/Projects/keras-yolo3-master/VOCdevkit/VOC2007/JPEGImages/3f14e5b775c1af77b3ee9dad6090e842_540.jpg</path>
	<source>
		<database>Unknown</database>
	</source>
	<size>
		<width>1920</width>
		<height>1080</height>
		<depth>3</depth>
	</size>
	<segmented>0</segmented>
	<object>
		<name>person</name>
		<pose>Unspecified</pose>
		<truncated>0</truncated>
		<difficult>0</difficult>
		<bndbox>
			<xmin>664.00</xmin>
			<ymin>162.61</ymin>
			<xmax>685.64</xmax>
			<ymax>243.40</ymax>
		</bndbox>
	</object>
	<object>
		<name>person</name>
		<pose>Unspecified</pose>
		<truncated>0</truncated>
		<difficult>0</difficult>
		<bndbox>
			<xmin>767.29</xmin>
			<ymin>171.92</ymin>
			<xmax>793.17</xmax>
			<ymax>247.20</ymax>
		</bndbox>
	</object>
</annotation>
