<?xml version="1.0" ?>
<annotation>
	<folder>JPEGImages</folder>
	<filename>3fd7a193c034cc21650d5a3b33800acc_120</filename>
	<path>C:/AIoT/Projects/keras-yolo3-master/VOCdevkit/VOC2007/JPEGImages/3fd7a193c034cc21650d5a3b33800acc_120.jpg</path>
	<source>
		<database>Unknown</database>
	</source>
	<size>
		<width>1920</width>
		<height>1080</height>
		<depth>3</depth>
	</size>
	<segmented>0</segmented>
	<object>
		<name>person</name>
		<pose>Unspecified</pose>
		<truncated>0</truncated>
		<difficult>0</difficult>
		<bndbox>
			<xmin>1137.98</xmin>
			<ymin>371.31</ymin>
			<xmax>1172.31</xmax>
			<ymax>392.96</ymax>
		</bndbox>
	</object>
	<object>
		<name>person</name>
		<pose>Unspecified</pose>
		<truncated>0</truncated>
		<difficult>0</difficult>
		<bndbox>
			<xmin>1143.61</xmin>
			<ymin>357.94</ymin>
			<xmax>1159.39</xmax>
			<ymax>386.59</ymax>
		</bndbox>
	</object>
	<object>
		<name>person</name>
		<pose>Unspecified</pose>
		<truncated>0</truncated>
		<difficult>0</difficult>
		<bndbox>
			<xmin>20.48</xmin>
			<ymin>402.81</ymin>
			<xmax>47.41</xmax>
			<ymax>519.36</ymax>
		</bndbox>
	</object>
	<object>
		<name>person</name>
		<pose>Unspecified</pose>
		<truncated>0</truncated>
		<difficult>0</difficult>
		<bndbox>
			<xmin>53.24</xmin>
			<ymin>401.35</ymin>
			<xmax>82.32</xmax>
			<ymax>511.48</ymax>
		</bndbox>
	</object>
	<object>
		<name>person</name>
		<pose>Unspecified</pose>
		<truncated>0</truncated>
		<difficult>0</difficult>
		<bndbox>
			<xmin>88.47</xmin>
			<ymin>401.84</ymin>
			<xmax>113.89</xmax>
			<ymax>483.85</ymax>
		</bndbox>
	</object>
	<object>
		<name>person</name>
		<pose>Unspecified</pose>
		<truncated>0</truncated>
		<difficult>0</difficult>
		<bndbox>
			<xmin>112.69</xmin>
			<ymin>399.87</ymin>
			<xmax>134.96</xmax>
			<ymax>444.73</ymax>
		</bndbox>
	</object>
	<object>
		<name>person</name>
		<pose>Unspecified</pose>
		<truncated>0</truncated>
		<difficult>0</difficult>
		<bndbox>
			<xmin>86.68</xmin>
			<ymin>440.83</ymin>
			<xmax>149.47</xmax>
			<ymax>503.62</ymax>
		</bndbox>
	</object>
	<object>
		<name>person</name>
		<pose>Unspecified</pose>
		<truncated>0</truncated>
		<difficult>0</difficult>
		<bndbox>
			<xmin>1773.88</xmin>
			<ymin>310.08</ymin>
			<xmax>1822.16</xmax>
			<ymax>476.15</ymax>
		</bndbox>
	</object>
	<object>
		<name>person</name>
		<pose>Unspecified</pose>
		<truncated>0</truncated>
		<difficult>0</difficult>
		<bndbox>
			<xmin>1194.80</xmin>
			<ymin>369.28</ymin>
			<xmax>1242.63</xmax>
			<ymax>402.50</ymax>
		</bndbox>
	</object>
	<object>
		<name>person</name>
		<pose>Unspecified</pose>
		<truncated>0</truncated>
		<difficult>0</difficult>
		<bndbox>
			<xmin>1208.73</xmin>
			<ymin>354.80</ymin>
			<xmax>1228.41</xmax>
			<ymax>396.38</ymax>
		</bndbox>
	</object>
	<object>
		<name>person</name>
		<pose>Unspecified</pose>
		<truncated>0</truncated>
		<difficult>0</difficult>
		<bndbox>
			<xmin>1268.75</xmin>
			<ymin>355.29</ymin>
			<xmax>1283.22</xmax>
			<ymax>386.22</ymax>
		</bndbox>
	</object>
</annotation>
