<?xml version="1.0" ?>
<annotation>
	<folder>JPEGImages</folder>
	<filename>46ef3f291fb521bce9a011f025acd2e7_150</filename>
	<path>C:/AIoT/Projects/keras-yolo3-master/VOCdevkit/VOC2007/JPEGImages/46ef3f291fb521bce9a011f025acd2e7_150.jpg</path>
	<source>
		<database>Unknown</database>
	</source>
	<size>
		<width>1920</width>
		<height>1080</height>
		<depth>3</depth>
	</size>
	<segmented>0</segmented>
	<object>
		<name>person</name>
		<pose>Unspecified</pose>
		<truncated>0</truncated>
		<difficult>0</difficult>
		<bndbox>
			<xmin>859.45</xmin>
			<ymin>254.71</ymin>
			<xmax>919.80</xmax>
			<ymax>381.50</ymax>
		</bndbox>
	</object>
	<object>
		<name>person</name>
		<pose>Unspecified</pose>
		<truncated>0</truncated>
		<difficult>0</difficult>
		<bndbox>
			<xmin>1151.30</xmin>
			<ymin>258.18</ymin>
			<xmax>1217.30</xmax>
			<ymax>448.80</ymax>
		</bndbox>
	</object>
	<object>
		<name>person</name>
		<pose>Unspecified</pose>
		<truncated>0</truncated>
		<difficult>0</difficult>
		<bndbox>
			<xmin>893.60</xmin>
			<ymin>241.19</ymin>
			<xmax>947.80</xmax>
			<ymax>388.10</ymax>
		</bndbox>
	</object>
</annotation>
