<?xml version="1.0" ?>
<annotation>
	<folder>JPEGImages</folder>
	<filename>47a5e617f70bc4a80b5de6d629290f2d_140</filename>
	<path>C:/AIoT/Projects/keras-yolo3-master/VOCdevkit/VOC2007/JPEGImages/47a5e617f70bc4a80b5de6d629290f2d_140.jpg</path>
	<source>
		<database>Unknown</database>
	</source>
	<size>
		<width>1920</width>
		<height>1080</height>
		<depth>3</depth>
	</size>
	<segmented>0</segmented>
	<object>
		<name>person</name>
		<pose>Unspecified</pose>
		<truncated>0</truncated>
		<difficult>0</difficult>
		<bndbox>
			<xmin>939.38</xmin>
			<ymin>382.49</ymin>
			<xmax>996.74</xmax>
			<ymax>515.94</ymax>
		</bndbox>
	</object>
	<object>
		<name>person</name>
		<pose>Unspecified</pose>
		<truncated>0</truncated>
		<difficult>0</difficult>
		<bndbox>
			<xmin>706.68</xmin>
			<ymin>356.70</ymin>
			<xmax>751.73</xmax>
			<ymax>503.37</ymax>
		</bndbox>
	</object>
</annotation>
