<?xml version="1.0" ?>
<annotation>
	<folder>JPEGImages</folder>
	<filename>50208b3aee22ff5231cc4c755c7fa325_10</filename>
	<path>C:/AIoT/Projects/keras-yolo3-master/VOCdevkit/VOC2007/JPEGImages/50208b3aee22ff5231cc4c755c7fa325_10.jpg</path>
	<source>
		<database>Unknown</database>
	</source>
	<size>
		<width>1920</width>
		<height>1080</height>
		<depth>3</depth>
	</size>
	<segmented>0</segmented>
	<object>
		<name>person</name>
		<pose>Unspecified</pose>
		<truncated>0</truncated>
		<difficult>0</difficult>
		<bndbox>
			<xmin>1213.00</xmin>
			<ymin>254.08</ymin>
			<xmax>1235.70</xmax>
			<ymax>326.60</ymax>
		</bndbox>
	</object>
	<object>
		<name>person</name>
		<pose>Unspecified</pose>
		<truncated>0</truncated>
		<difficult>0</difficult>
		<bndbox>
			<xmin>1099.82</xmin>
			<ymin>246.84</ymin>
			<xmax>1113.93</xmax>
			<ymax>285.37</ymax>
		</bndbox>
	</object>
</annotation>
