<?xml version="1.0" ?>
<annotation>
	<folder>JPEGImages</folder>
	<filename>6011973b95548aac87ea4b2cd8a0177b_280</filename>
	<path>C:/AIoT/Projects/keras-yolo3-master/VOCdevkit/VOC2007/JPEGImages/6011973b95548aac87ea4b2cd8a0177b_280.jpg</path>
	<source>
		<database>Unknown</database>
	</source>
	<size>
		<width>1920</width>
		<height>1080</height>
		<depth>3</depth>
	</size>
	<segmented>0</segmented>
	<object>
		<name>person</name>
		<pose>Unspecified</pose>
		<truncated>0</truncated>
		<difficult>0</difficult>
		<bndbox>
			<xmin>1143.75</xmin>
			<ymin>200.84</ymin>
			<xmax>1153.17</xmax>
			<ymax>217.93</ymax>
		</bndbox>
	</object>
	<object>
		<name>person</name>
		<pose>Unspecified</pose>
		<truncated>0</truncated>
		<difficult>0</difficult>
		<bndbox>
			<xmin>1122.30</xmin>
			<ymin>200.98</ymin>
			<xmax>1131.70</xmax>
			<ymax>216.49</ymax>
		</bndbox>
	</object>
	<object>
		<name>person</name>
		<pose>Unspecified</pose>
		<truncated>0</truncated>
		<difficult>0</difficult>
		<bndbox>
			<xmin>330.97</xmin>
			<ymin>221.70</ymin>
			<xmax>349.85</xmax>
			<ymax>258.26</ymax>
		</bndbox>
	</object>
	<object>
		<name>person</name>
		<pose>Unspecified</pose>
		<truncated>0</truncated>
		<difficult>0</difficult>
		<bndbox>
			<xmin>450.64</xmin>
			<ymin>223.19</ymin>
			<xmax>463.30</xmax>
			<ymax>243.08</ymax>
		</bndbox>
	</object>
	<object>
		<name>person</name>
		<pose>Unspecified</pose>
		<truncated>0</truncated>
		<difficult>0</difficult>
		<bndbox>
			<xmin>1153.05</xmin>
			<ymin>200.86</ymin>
			<xmax>1170.85</xmax>
			<ymax>228.59</ymax>
		</bndbox>
	</object>
</annotation>
