<?xml version="1.0" ?>
<annotation>
	<folder>JPEGImages</folder>
	<filename>6a899286349ba557159b7b6688bd58d4_680</filename>
	<path>C:/AIoT/Projects/keras-yolo3-master/VOCdevkit/VOC2007/JPEGImages/6a899286349ba557159b7b6688bd58d4_680.jpg</path>
	<source>
		<database>Unknown</database>
	</source>
	<size>
		<width>1920</width>
		<height>1080</height>
		<depth>3</depth>
	</size>
	<segmented>0</segmented>
	<object>
		<name>person</name>
		<pose>Unspecified</pose>
		<truncated>0</truncated>
		<difficult>0</difficult>
		<bndbox>
			<xmin>322.63</xmin>
			<ymin>145.41</ymin>
			<xmax>342.73</xmax>
			<ymax>214.88</ymax>
		</bndbox>
	</object>
	<object>
		<name>person</name>
		<pose>Unspecified</pose>
		<truncated>0</truncated>
		<difficult>0</difficult>
		<bndbox>
			<xmin>333.95</xmin>
			<ymin>147.74</ymin>
			<xmax>348.60</xmax>
			<ymax>202.37</ymax>
		</bndbox>
	</object>
	<object>
		<name>person</name>
		<pose>Unspecified</pose>
		<truncated>0</truncated>
		<difficult>0</difficult>
		<bndbox>
			<xmin>519.39</xmin>
			<ymin>136.25</ymin>
			<xmax>541.50</xmax>
			<ymax>219.60</ymax>
		</bndbox>
	</object>
</annotation>
