<?xml version="1.0" ?>
<annotation>
	<folder>JPEGImages</folder>
	<filename>79a347b0d37f254d37c37560b8bfa2c1_410</filename>
	<path>C:/AIoT/Projects/keras-yolo3-master/VOCdevkit/VOC2007/JPEGImages/79a347b0d37f254d37c37560b8bfa2c1_410.jpg</path>
	<source>
		<database>Unknown</database>
	</source>
	<size>
		<width>1920</width>
		<height>1080</height>
		<depth>3</depth>
	</size>
	<segmented>0</segmented>
	<object>
		<name>person</name>
		<pose>Unspecified</pose>
		<truncated>0</truncated>
		<difficult>0</difficult>
		<bndbox>
			<xmin>1060.81</xmin>
			<ymin>374.30</ymin>
			<xmax>1121.50</xmax>
			<ymax>485.30</ymax>
		</bndbox>
	</object>
	<object>
		<name>person</name>
		<pose>Unspecified</pose>
		<truncated>0</truncated>
		<difficult>0</difficult>
		<bndbox>
			<xmin>1016.19</xmin>
			<ymin>378.00</ymin>
			<xmax>1051.08</xmax>
			<ymax>478.06</ymax>
		</bndbox>
	</object>
	<object>
		<name>person</name>
		<pose>Unspecified</pose>
		<truncated>0</truncated>
		<difficult>0</difficult>
		<bndbox>
			<xmin>451.29</xmin>
			<ymin>359.25</ymin>
			<xmax>544.79</xmax>
			<ymax>550.13</ymax>
		</bndbox>
	</object>
	<object>
		<name>person</name>
		<pose>Unspecified</pose>
		<truncated>0</truncated>
		<difficult>0</difficult>
		<bndbox>
			<xmin>816.62</xmin>
			<ymin>345.77</ymin>
			<xmax>867.20</xmax>
			<ymax>539.44</ymax>
		</bndbox>
	</object>
	<object>
		<name>person</name>
		<pose>Unspecified</pose>
		<truncated>0</truncated>
		<difficult>0</difficult>
		<bndbox>
			<xmin>363.03</xmin>
			<ymin>387.03</ymin>
			<xmax>383.63</xmax>
			<ymax>461.50</ymax>
		</bndbox>
	</object>
	<object>
		<name>person</name>
		<pose>Unspecified</pose>
		<truncated>0</truncated>
		<difficult>0</difficult>
		<bndbox>
			<xmin>602.18</xmin>
			<ymin>391.79</ymin>
			<xmax>636.39</xmax>
			<ymax>432.93</ymax>
		</bndbox>
	</object>
	<object>
		<name>person</name>
		<pose>Unspecified</pose>
		<truncated>0</truncated>
		<difficult>0</difficult>
		<bndbox>
			<xmin>417.62</xmin>
			<ymin>384.97</ymin>
			<xmax>432.14</xmax>
			<ymax>432.39</ymax>
		</bndbox>
	</object>
	<object>
		<name>person</name>
		<pose>Unspecified</pose>
		<truncated>0</truncated>
		<difficult>0</difficult>
		<bndbox>
			<xmin>432.29</xmin>
			<ymin>385.56</ymin>
			<xmax>443.99</xmax>
			<ymax>432.75</ymax>
		</bndbox>
	</object>
</annotation>
