<?xml version="1.0" ?>
<annotation>
	<folder>JPEGImages</folder>
	<filename>7a6d3b7f10476923babef74d479128f5_680</filename>
	<path>C:/AIoT/Projects/keras-yolo3-master/VOCdevkit/VOC2007/JPEGImages/7a6d3b7f10476923babef74d479128f5_680.jpg</path>
	<source>
		<database>Unknown</database>
	</source>
	<size>
		<width>1920</width>
		<height>1080</height>
		<depth>3</depth>
	</size>
	<segmented>0</segmented>
	<object>
		<name>person</name>
		<pose>Unspecified</pose>
		<truncated>0</truncated>
		<difficult>0</difficult>
		<bndbox>
			<xmin>1301.36</xmin>
			<ymin>491.43</ymin>
			<xmax>1343.17</xmax>
			<ymax>570.71</ymax>
		</bndbox>
	</object>
	<object>
		<name>person</name>
		<pose>Unspecified</pose>
		<truncated>0</truncated>
		<difficult>0</difficult>
		<bndbox>
			<xmin>1410.39</xmin>
			<ymin>487.12</ymin>
			<xmax>1439.86</xmax>
			<ymax>558.35</ymax>
		</bndbox>
	</object>
	<object>
		<name>person</name>
		<pose>Unspecified</pose>
		<truncated>0</truncated>
		<difficult>0</difficult>
		<bndbox>
			<xmin>1259.05</xmin>
			<ymin>489.75</ymin>
			<xmax>1279.17</xmax>
			<ymax>548.61</ymax>
		</bndbox>
	</object>
	<object>
		<name>person</name>
		<pose>Unspecified</pose>
		<truncated>0</truncated>
		<difficult>0</difficult>
		<bndbox>
			<xmin>1218.58</xmin>
			<ymin>490.77</ymin>
			<xmax>1232.34</xmax>
			<ymax>541.73</ymax>
		</bndbox>
	</object>
	<object>
		<name>person</name>
		<pose>Unspecified</pose>
		<truncated>0</truncated>
		<difficult>0</difficult>
		<bndbox>
			<xmin>1200.31</xmin>
			<ymin>493.51</ymin>
			<xmax>1211.95</xmax>
			<ymax>536.78</ymax>
		</bndbox>
	</object>
	<object>
		<name>person</name>
		<pose>Unspecified</pose>
		<truncated>0</truncated>
		<difficult>0</difficult>
		<bndbox>
			<xmin>1366.86</xmin>
			<ymin>485.53</ymin>
			<xmax>1394.74</xmax>
			<ymax>568.72</ymax>
		</bndbox>
	</object>
</annotation>
