<?xml version="1.0" ?>
<annotation>
	<folder>JPEGImages</folder>
	<filename>7f3c551b074c624cafc7eb3c672e7e19_290</filename>
	<path>C:/AIoT/Projects/keras-yolo3-master/VOCdevkit/VOC2007/JPEGImages/7f3c551b074c624cafc7eb3c672e7e19_290.jpg</path>
	<source>
		<database>Unknown</database>
	</source>
	<size>
		<width>1920</width>
		<height>1080</height>
		<depth>3</depth>
	</size>
	<segmented>0</segmented>
	<object>
		<name>person</name>
		<pose>Unspecified</pose>
		<truncated>0</truncated>
		<difficult>0</difficult>
		<bndbox>
			<xmin>1010.41</xmin>
			<ymin>186.53</ymin>
			<xmax>1021.21</xmax>
			<ymax>216.62</ymax>
		</bndbox>
	</object>
	<object>
		<name>person</name>
		<pose>Unspecified</pose>
		<truncated>0</truncated>
		<difficult>0</difficult>
		<bndbox>
			<xmin>1001.60</xmin>
			<ymin>190.36</ymin>
			<xmax>1010.91</xmax>
			<ymax>215.09</ymax>
		</bndbox>
	</object>
</annotation>
