<?xml version="1.0" ?>
<annotation>
	<folder>JPEGImages</folder>
	<filename>8e2b6585228e3b1b71696c2b0d9113d7_480</filename>
	<path>C:/AIoT/Projects/keras-yolo3-master/VOCdevkit/VOC2007/JPEGImages/8e2b6585228e3b1b71696c2b0d9113d7_480.jpg</path>
	<source>
		<database>Unknown</database>
	</source>
	<size>
		<width>1920</width>
		<height>1080</height>
		<depth>3</depth>
	</size>
	<segmented>0</segmented>
	<object>
		<name>person</name>
		<pose>Unspecified</pose>
		<truncated>0</truncated>
		<difficult>0</difficult>
		<bndbox>
			<xmin>1733.24</xmin>
			<ymin>216.72</ymin>
			<xmax>1766.33</xmax>
			<ymax>273.66</ymax>
		</bndbox>
	</object>
	<object>
		<name>person</name>
		<pose>Unspecified</pose>
		<truncated>0</truncated>
		<difficult>0</difficult>
		<bndbox>
			<xmin>1600.21</xmin>
			<ymin>228.92</ymin>
			<xmax>1623.53</xmax>
			<ymax>310.70</ymax>
		</bndbox>
	</object>
	<object>
		<name>person</name>
		<pose>Unspecified</pose>
		<truncated>0</truncated>
		<difficult>0</difficult>
		<bndbox>
			<xmin>1421.84</xmin>
			<ymin>300.31</ymin>
			<xmax>1463.47</xmax>
			<ymax>339.61</ymax>
		</bndbox>
	</object>
	<object>
		<name>person</name>
		<pose>Unspecified</pose>
		<truncated>0</truncated>
		<difficult>0</difficult>
		<bndbox>
			<xmin>1232.25</xmin>
			<ymin>203.05</ymin>
			<xmax>1252.50</xmax>
			<ymax>261.13</ymax>
		</bndbox>
	</object>
	<object>
		<name>person</name>
		<pose>Unspecified</pose>
		<truncated>0</truncated>
		<difficult>0</difficult>
		<bndbox>
			<xmin>1175.38</xmin>
			<ymin>206.83</ymin>
			<xmax>1184.01</xmax>
			<ymax>242.85</ymax>
		</bndbox>
	</object>
	<object>
		<name>person</name>
		<pose>Unspecified</pose>
		<truncated>0</truncated>
		<difficult>0</difficult>
		<bndbox>
			<xmin>1163.53</xmin>
			<ymin>208.79</ymin>
			<xmax>1177.52</xmax>
			<ymax>246.81</ymax>
		</bndbox>
	</object>
	<object>
		<name>person</name>
		<pose>Unspecified</pose>
		<truncated>0</truncated>
		<difficult>0</difficult>
		<bndbox>
			<xmin>1219.80</xmin>
			<ymin>210.03</ymin>
			<xmax>1228.05</xmax>
			<ymax>234.06</ymax>
		</bndbox>
	</object>
	<object>
		<name>person</name>
		<pose>Unspecified</pose>
		<truncated>0</truncated>
		<difficult>0</difficult>
		<bndbox>
			<xmin>880.84</xmin>
			<ymin>189.73</ymin>
			<xmax>940.94</xmax>
			<ymax>315.66</ymax>
		</bndbox>
	</object>
	<object>
		<name>person</name>
		<pose>Unspecified</pose>
		<truncated>0</truncated>
		<difficult>0</difficult>
		<bndbox>
			<xmin>1036.22</xmin>
			<ymin>179.02</ymin>
			<xmax>1120.91</xmax>
			<ymax>380.75</ymax>
		</bndbox>
	</object>
</annotation>
