<?xml version="1.0" ?>
<annotation>
	<folder>JPEGImages</folder>
	<filename>a3a9142d4d1146671b44c5cd995f416f_240</filename>
	<path>C:/AIoT/Projects/keras-yolo3-master/VOCdevkit/VOC2007/JPEGImages/a3a9142d4d1146671b44c5cd995f416f_240.jpg</path>
	<source>
		<database>Unknown</database>
	</source>
	<size>
		<width>1920</width>
		<height>1080</height>
		<depth>3</depth>
	</size>
	<segmented>0</segmented>
	<object>
		<name>person</name>
		<pose>Unspecified</pose>
		<truncated>0</truncated>
		<difficult>0</difficult>
		<bndbox>
			<xmin>1654.41</xmin>
			<ymin>248.38</ymin>
			<xmax>1682.30</xmax>
			<ymax>357.70</ymax>
		</bndbox>
	</object>
	<object>
		<name>person</name>
		<pose>Unspecified</pose>
		<truncated>0</truncated>
		<difficult>0</difficult>
		<bndbox>
			<xmin>1550.95</xmin>
			<ymin>245.10</ymin>
			<xmax>1572.09</xmax>
			<ymax>316.49</ymax>
		</bndbox>
	</object>
	<object>
		<name>person</name>
		<pose>Unspecified</pose>
		<truncated>0</truncated>
		<difficult>0</difficult>
		<bndbox>
			<xmin>1600.00</xmin>
			<ymin>252.91</ymin>
			<xmax>1622.20</xmax>
			<ymax>325.32</ymax>
		</bndbox>
	</object>
	<object>
		<name>person</name>
		<pose>Unspecified</pose>
		<truncated>0</truncated>
		<difficult>0</difficult>
		<bndbox>
			<xmin>1397.22</xmin>
			<ymin>247.64</ymin>
			<xmax>1417.01</xmax>
			<ymax>304.04</ymax>
		</bndbox>
	</object>
</annotation>
