<?xml version="1.0" ?>
<annotation>
	<folder>JPEGImages</folder>
	<filename>abf90582d755220b6fea445c304a8dbe_120</filename>
	<path>C:/AIoT/Projects/keras-yolo3-master/VOCdevkit/VOC2007/JPEGImages/abf90582d755220b6fea445c304a8dbe_120.jpg</path>
	<source>
		<database>Unknown</database>
	</source>
	<size>
		<width>1920</width>
		<height>1080</height>
		<depth>3</depth>
	</size>
	<segmented>0</segmented>
	<object>
		<name>person</name>
		<pose>Unspecified</pose>
		<truncated>0</truncated>
		<difficult>0</difficult>
		<bndbox>
			<xmin>65.69</xmin>
			<ymin>344.34</ymin>
			<xmax>96.79</xmax>
			<ymax>416.90</ymax>
		</bndbox>
	</object>
	<object>
		<name>person</name>
		<pose>Unspecified</pose>
		<truncated>0</truncated>
		<difficult>0</difficult>
		<bndbox>
			<xmin>151.51</xmin>
			<ymin>353.01</ymin>
			<xmax>166.94</xmax>
			<ymax>386.94</ymax>
		</bndbox>
	</object>
	<object>
		<name>person</name>
		<pose>Unspecified</pose>
		<truncated>0</truncated>
		<difficult>0</difficult>
		<bndbox>
			<xmin>723.40</xmin>
			<ymin>354.00</ymin>
			<xmax>735.69</xmax>
			<ymax>379.80</ymax>
		</bndbox>
	</object>
	<object>
		<name>person</name>
		<pose>Unspecified</pose>
		<truncated>0</truncated>
		<difficult>0</difficult>
		<bndbox>
			<xmin>645.61</xmin>
			<ymin>352.27</ymin>
			<xmax>659.51</xmax>
			<ymax>376.73</ymax>
		</bndbox>
	</object>
</annotation>
