<?xml version="1.0" ?>
<annotation>
	<folder>JPEGImages</folder>
	<filename>bc9b6eeb70db2a4d3609f72e0d7c4580_20</filename>
	<path>C:/AIoT/Projects/keras-yolo3-master/VOCdevkit/VOC2007/JPEGImages/bc9b6eeb70db2a4d3609f72e0d7c4580_20.jpg</path>
	<source>
		<database>Unknown</database>
	</source>
	<size>
		<width>1920</width>
		<height>1080</height>
		<depth>3</depth>
	</size>
	<segmented>0</segmented>
	<object>
		<name>person</name>
		<pose>Unspecified</pose>
		<truncated>0</truncated>
		<difficult>0</difficult>
		<bndbox>
			<xmin>734.73</xmin>
			<ymin>275.08</ymin>
			<xmax>752.43</xmax>
			<ymax>316.52</ymax>
		</bndbox>
	</object>
	<object>
		<name>person</name>
		<pose>Unspecified</pose>
		<truncated>0</truncated>
		<difficult>0</difficult>
		<bndbox>
			<xmin>1186.90</xmin>
			<ymin>269.28</ymin>
			<xmax>1209.84</xmax>
			<ymax>356.60</ymax>
		</bndbox>
	</object>
	<object>
		<name>person</name>
		<pose>Unspecified</pose>
		<truncated>0</truncated>
		<difficult>0</difficult>
		<bndbox>
			<xmin>629.02</xmin>
			<ymin>279.25</ymin>
			<xmax>649.29</xmax>
			<ymax>339.17</ymax>
		</bndbox>
	</object>
	<object>
		<name>person</name>
		<pose>Unspecified</pose>
		<truncated>0</truncated>
		<difficult>0</difficult>
		<bndbox>
			<xmin>770.09</xmin>
			<ymin>270.85</ymin>
			<xmax>787.38</xmax>
			<ymax>315.82</ymax>
		</bndbox>
	</object>
	<object>
		<name>person</name>
		<pose>Unspecified</pose>
		<truncated>0</truncated>
		<difficult>0</difficult>
		<bndbox>
			<xmin>1244.52</xmin>
			<ymin>267.62</ymin>
			<xmax>1279.03</xmax>
			<ymax>356.65</ymax>
		</bndbox>
	</object>
	<object>
		<name>person</name>
		<pose>Unspecified</pose>
		<truncated>0</truncated>
		<difficult>0</difficult>
		<bndbox>
			<xmin>1207.76</xmin>
			<ymin>280.99</ymin>
			<xmax>1237.30</xmax>
			<ymax>362.10</ymax>
		</bndbox>
	</object>
	<object>
		<name>person</name>
		<pose>Unspecified</pose>
		<truncated>0</truncated>
		<difficult>0</difficult>
		<bndbox>
			<xmin>1095.62</xmin>
			<ymin>273.59</ymin>
			<xmax>1139.66</xmax>
			<ymax>350.92</ymax>
		</bndbox>
	</object>
</annotation>
