<?xml version="1.0" ?>
<annotation>
	<folder>JPEGImages</folder>
	<filename>c1d0a091f49c44956b47b097f2c4b5ed_590</filename>
	<path>C:/AIoT/Projects/keras-yolo3-master/VOCdevkit/VOC2007/JPEGImages/c1d0a091f49c44956b47b097f2c4b5ed_590.jpg</path>
	<source>
		<database>Unknown</database>
	</source>
	<size>
		<width>1920</width>
		<height>1080</height>
		<depth>3</depth>
	</size>
	<segmented>0</segmented>
	<object>
		<name>person</name>
		<pose>Unspecified</pose>
		<truncated>0</truncated>
		<difficult>0</difficult>
		<bndbox>
			<xmin>1488.12</xmin>
			<ymin>450.79</ymin>
			<xmax>1549.75</xmax>
			<ymax>616.55</ymax>
		</bndbox>
	</object>
</annotation>
