<?xml version="1.0" ?>
<annotation>
	<folder>JPEGImages</folder>
	<filename>c44fa0b847fac3f67a64a3671cf42b23_330</filename>
	<path>C:/AIoT/Projects/keras-yolo3-master/VOCdevkit/VOC2007/JPEGImages/c44fa0b847fac3f67a64a3671cf42b23_330.jpg</path>
	<source>
		<database>Unknown</database>
	</source>
	<size>
		<width>1920</width>
		<height>1080</height>
		<depth>3</depth>
	</size>
	<segmented>0</segmented>
	<object>
		<name>person</name>
		<pose>Unspecified</pose>
		<truncated>0</truncated>
		<difficult>0</difficult>
		<bndbox>
			<xmin>920.00</xmin>
			<ymin>220.36</ymin>
			<xmax>941.71</xmax>
			<ymax>262.82</ymax>
		</bndbox>
	</object>
	<object>
		<name>person</name>
		<pose>Unspecified</pose>
		<truncated>0</truncated>
		<difficult>0</difficult>
		<bndbox>
			<xmin>1134.64</xmin>
			<ymin>216.29</ymin>
			<xmax>1154.85</xmax>
			<ymax>236.78</ymax>
		</bndbox>
	</object>
	<object>
		<name>person</name>
		<pose>Unspecified</pose>
		<truncated>0</truncated>
		<difficult>0</difficult>
		<bndbox>
			<xmin>1030.30</xmin>
			<ymin>216.75</ymin>
			<xmax>1049.77</xmax>
			<ymax>267.01</ymax>
		</bndbox>
	</object>
	<object>
		<name>person</name>
		<pose>Unspecified</pose>
		<truncated>0</truncated>
		<difficult>0</difficult>
		<bndbox>
			<xmin>1068.58</xmin>
			<ymin>207.59</ymin>
			<xmax>1085.20</xmax>
			<ymax>239.20</ymax>
		</bndbox>
	</object>
</annotation>
