<?xml version="1.0" ?>
<annotation>
	<folder>JPEGImages</folder>
	<filename>cebc8f5631896342bde3379464db8319_420</filename>
	<path>C:/AIoT/Projects/keras-yolo3-master/VOCdevkit/VOC2007/JPEGImages/cebc8f5631896342bde3379464db8319_420.jpg</path>
	<source>
		<database>Unknown</database>
	</source>
	<size>
		<width>1920</width>
		<height>1080</height>
		<depth>3</depth>
	</size>
	<segmented>0</segmented>
	<object>
		<name>person</name>
		<pose>Unspecified</pose>
		<truncated>0</truncated>
		<difficult>0</difficult>
		<bndbox>
			<xmin>1075.30</xmin>
			<ymin>531.87</ymin>
			<xmax>1095.10</xmax>
			<ymax>570.30</ymax>
		</bndbox>
	</object>
	<object>
		<name>person</name>
		<pose>Unspecified</pose>
		<truncated>0</truncated>
		<difficult>0</difficult>
		<bndbox>
			<xmin>1023.02</xmin>
			<ymin>524.68</ymin>
			<xmax>1038.40</xmax>
			<ymax>574.50</ymax>
		</bndbox>
	</object>
	<object>
		<name>person</name>
		<pose>Unspecified</pose>
		<truncated>0</truncated>
		<difficult>0</difficult>
		<bndbox>
			<xmin>552.37</xmin>
			<ymin>522.68</ymin>
			<xmax>570.16</xmax>
			<ymax>566.39</ymax>
		</bndbox>
	</object>
</annotation>
