<?xml version="1.0" ?>
<annotation>
	<folder>JPEGImages</folder>
	<filename>d0e5b5937540567d2eb3d486575e8403_270</filename>
	<path>C:/AIoT/Projects/keras-yolo3-master/VOCdevkit/VOC2007/JPEGImages/d0e5b5937540567d2eb3d486575e8403_270.jpg</path>
	<source>
		<database>Unknown</database>
	</source>
	<size>
		<width>1920</width>
		<height>1080</height>
		<depth>3</depth>
	</size>
	<segmented>0</segmented>
	<object>
		<name>person</name>
		<pose>Unspecified</pose>
		<truncated>0</truncated>
		<difficult>0</difficult>
		<bndbox>
			<xmin>1889.00</xmin>
			<ymin>258.53</ymin>
			<xmax>1916.20</xmax>
			<ymax>443.80</ymax>
		</bndbox>
	</object>
	<object>
		<name>person</name>
		<pose>Unspecified</pose>
		<truncated>0</truncated>
		<difficult>0</difficult>
		<bndbox>
			<xmin>403.95</xmin>
			<ymin>168.12</ymin>
			<xmax>443.28</xmax>
			<ymax>321.16</ymax>
		</bndbox>
	</object>
</annotation>
