<?xml version="1.0" ?>
<annotation>
	<folder>JPEGImages</folder>
	<filename>da7b4df9b58b0b796afe2f8cc136c0d2_540</filename>
	<path>C:/AIoT/Projects/keras-yolo3-master/VOCdevkit/VOC2007/JPEGImages/da7b4df9b58b0b796afe2f8cc136c0d2_540.jpg</path>
	<source>
		<database>Unknown</database>
	</source>
	<size>
		<width>1920</width>
		<height>1080</height>
		<depth>3</depth>
	</size>
	<segmented>0</segmented>
	<object>
		<name>person</name>
		<pose>Unspecified</pose>
		<truncated>0</truncated>
		<difficult>0</difficult>
		<bndbox>
			<xmin>832.28</xmin>
			<ymin>207.68</ymin>
			<xmax>840.94</xmax>
			<ymax>238.73</ymax>
		</bndbox>
	</object>
</annotation>
