<?xml version="1.0" ?>
<annotation>
	<folder>JPEGImages</folder>
	<filename>f5776b7710e6f260489166969207a40e_470</filename>
	<path>C:/AIoT/Projects/keras-yolo3-master/VOCdevkit/VOC2007/JPEGImages/f5776b7710e6f260489166969207a40e_470.jpg</path>
	<source>
		<database>Unknown</database>
	</source>
	<size>
		<width>1920</width>
		<height>1080</height>
		<depth>3</depth>
	</size>
	<segmented>0</segmented>
	<object>
		<name>person</name>
		<pose>Unspecified</pose>
		<truncated>0</truncated>
		<difficult>0</difficult>
		<bndbox>
			<xmin>255.26</xmin>
			<ymin>302.78</ymin>
			<xmax>278.44</xmax>
			<ymax>357.04</ymax>
		</bndbox>
	</object>
	<object>
		<name>person</name>
		<pose>Unspecified</pose>
		<truncated>0</truncated>
		<difficult>0</difficult>
		<bndbox>
			<xmin>337.42</xmin>
			<ymin>292.57</ymin>
			<xmax>356.26</xmax>
			<ymax>343.61</ymax>
		</bndbox>
	</object>
	<object>
		<name>person</name>
		<pose>Unspecified</pose>
		<truncated>0</truncated>
		<difficult>0</difficult>
		<bndbox>
			<xmin>1891.60</xmin>
			<ymin>351.46</ymin>
			<xmax>1917.97</xmax>
			<ymax>436.57</ymax>
		</bndbox>
	</object>
	<object>
		<name>person</name>
		<pose>Unspecified</pose>
		<truncated>0</truncated>
		<difficult>0</difficult>
		<bndbox>
			<xmin>1362.25</xmin>
			<ymin>303.22</ymin>
			<xmax>1387.24</xmax>
			<ymax>364.36</ymax>
		</bndbox>
	</object>
	<object>
		<name>person</name>
		<pose>Unspecified</pose>
		<truncated>0</truncated>
		<difficult>0</difficult>
		<bndbox>
			<xmin>1819.47</xmin>
			<ymin>344.69</ymin>
			<xmax>1847.10</xmax>
			<ymax>406.16</ymax>
		</bndbox>
	</object>
</annotation>
